[{"number":"365","modality":"Modalidade","object":"Compra de mesas","trading_date":"2017-12-19"},{"number":"64","modality":"Outro tipo de modalidade","object":"Compra de canetas","trading_date":"2017-12-26"},{"number":"64","modality":"Outro tipo de modalidade","object":"Compra de canetas","trading_date":"2017-12-26"},{"number":"21","modality":"Tomada de Pre\u00e7o","object":"compra de borracha","trading_date":"2017-12-27"},{"number":"365","modality":"Tomada de Pre\u00e7o","object":"compra de equipamento de limpeza","trading_date":"2017-12-28"},{"number":"214","modality":"Tomada de Pre\u00e7o","object":"compra de estojo","trading_date":"2017-12-27"},{"number":"214","modality":"Tomada de Pre\u00e7o","object":"compra de estojo","trading_date":"2017-12-27"},{"number":"1","modality":"Tomada de Pre\u00e7o","object":"compra de dinheiro","trading_date":"2017-12-22"},{"number":"214","modality":"Outro tipo de modalidade","object":"compra de maleta","trading_date":"2017-12-21"},{"number":"66","modality":"Tomada de Pre\u00e7o","object":"compra de papel","trading_date":"2017-12-20"},{"number":"36","modality":"Tomada de Pre\u00e7o","object":"compra de \u00e1gua","trading_date":"2017-12-20"},{"number":"2457","modality":"Modalidade","object":"compra de sapatos ","trading_date":"2017-12-28"}]